assignbot/__init__.py
assignbot/__main__.py
assignbot/s3_utils.py
assignbot-2.2.2.dist-info/COPYING
assignbot-2.2.2.dist-info/METADATA
assignbot-2.2.2.dist-info/WHEEL
assignbot-2.2.2.dist-info/entry_points.txt
assignbot-2.2.2.dist-info/top_level.txt
assignbot-2.2.2.dist-info/RECORD
