Metadata-Version: 2.1
Name: assignbot
Version: 2.2.2
Summary: Automatically assign review on gitlab/heptapod
Home-page: https://forge.extranet.logilab.fr/open-source/assignbot
Author: Logilab
Author-email: contact@logilab.fr
License: LGPL
Platform: UNKNOWN
Classifier: Development Status :: 2 - Pre-Alpha
Classifier: Intended Audience :: Developers
Classifier: Natural Language :: English
Classifier: Programming Language :: Python :: 3
Classifier: Programming Language :: Python :: 3.6
Classifier: Programming Language :: Python :: 3.7
Classifier: Programming Language :: Python :: 3.8
Requires-Python: >=3.6
License-File: COPYING
Requires-Dist: python-gitlab
Requires-Dist: pyyaml
Requires-Dist: pandas
Requires-Dist: boto3
